mpdbapi/__init__.py
mpdbapi/data_classes.py
mpdbapi/exceptions.py
mpdbapi/mpdbapi.py
mpdbapi/responses.py
mpdbapi/utils.py
TheMPDBApiSdk-1.4.4.dist-info/METADATA
TheMPDBApiSdk-1.4.4.dist-info/WHEEL
TheMPDBApiSdk-1.4.4.dist-info/top_level.txt
TheMPDBApiSdk-1.4.4.dist-info/RECORD
