Metadata-Version: 2.1
Name: TheMPDBApiSdk
Version: 1.4.4
Summary: An easy sdk for using https://api.thempdb.org
Home-page: https://thempdb.org
Author: TheMPDB
Author-email: mandiracieyuphan@gmail.com
License: MIT
Requires-Dist: requests
